py934/__init__.py
py934/constant.py
py934/jubjub.py
py934/mimblewimble.py
py934/mmr.py
py934/rollup.py
py934-0.0.1.dist-info/LICENSE
py934-0.0.1.dist-info/METADATA
py934-0.0.1.dist-info/WHEEL
py934-0.0.1.dist-info/top_level.txt
py934-0.0.1.dist-info/RECORD
