Metadata-Version: 2.1
Name: py934
Version: 0.0.1
Summary: Python library for Ethereum 9 3/4
Home-page: https://github.com/ethereum/eth-mimblewimble
Author: Wanseob Lim
Author-email: email@wanseob.com
License: UNKNOWN
Platform: UNKNOWN
Classifier: Programming Language :: Python :: 3
Classifier: License :: OSI Approved :: GNU Library or Lesser General Public License (LGPL)
Classifier: Operating System :: OS Independent
Requires-Dist: ethsnarks (==0.0.1)
Requires-Dist: web3 (==5.0.1)
Requires-Dist: docker (==4.0.2)
